enemizer/__init__.py
enemizer/__main__.py
enemizer/enemizer.py
enemizer/enemizer_config.py
enemizer/generator.py
enemizer/utils.py
enemizer/data/defaults.sbyml
Enemizer-2.1.3.dist-info/METADATA
Enemizer-2.1.3.dist-info/WHEEL
Enemizer-2.1.3.dist-info/entry_points.txt
Enemizer-2.1.3.dist-info/top_level.txt
Enemizer-2.1.3.dist-info/RECORD
