Metadata-Version: 2.1
Name: Enemizer
Version: 2.1.3
Summary: Breath of the Wild Enemy Randomizer v2 by Echocolat
Home-page: https://github.com/Echocolat/EnemyRandomizerComplete
Author: Echocolat
Author-email: 
Classifier: Development Status :: 5 - Production/Stable
Classifier: Environment :: Console
Classifier: License :: OSI Approved :: GNU General Public License v3 or later (GPLv3+)
Classifier: Operating System :: OS Independent
Classifier: Programming Language :: Python :: 3 :: Only
Requires-Python: >=3.7
Requires-Dist: bcml (>=3.8.6)
Requires-Dist: oead (~=1.2.0)
Requires-Dist: botw-flag-util (>=0.3.5)
